semontology/__init__.py
semontology-0.0.1.dist-info/LICENSE
semontology-0.0.1.dist-info/METADATA
semontology-0.0.1.dist-info/WHEEL
semontology-0.0.1.dist-info/top_level.txt
semontology-0.0.1.dist-info/RECORD
