Metadata-Version: 2.1
Name: semontology
Version: 0.0.1
Summary: semontology
Home-page: https://github.com/Zharkov/semontology
Author: Zharkov A.P.
Author-email: antonzharckov@yandex.ru
License: UNKNOWN
Platform: UNKNOWN
Requires-Python: >=3.8
